{
  "docs": {
    "Chorus Cloud": [
      "ChorusCloudOverview"
    ],
    "Remits": [
      "RemitsOverview",
      {
        "type": "subcategory",
        "label": "Getting Started",
        "ids": [
          "Remits/Installation",
          "Remits/Connection",
          "Remits/ClaimLifecycle"
        ]
      },
      {
        "type": "subcategory",
        "label": "Remittance Advices",
        "ids": [
          "Remits/RemitsOverview",
          "Remits/PaymentsOverview"
        ]
      },
      {
        "type": "subcategory",
        "label": "Claims",
        "ids": [
          "Remits/ClaimsOverview",
          "Remits/SearchClaim"
        ]
      }

    ],
    "Eligibility": [
      "Eligibility/EligibilityOverview",
      {
        "type": "subcategory",
        "label": "Getting Started",
        "ids": [
          "Eligibility/Getting-Started/EligibilityInstallation",
          "Eligibility/Getting-Started/Subscriptions",
          "Eligibility/Getting-Started/ClearingHouseSubmitter",
          "Eligibility/Getting-Started/SecurityRoles"
        ]
      },
      {
        "type": "subcategory",
        "label": "Eligibility Requests",
        "ids": [
          "Eligibility/EligibilityRequest",
          "Eligibility/Coverage",
          "Eligibility/DynamicsHealthIntegration"
        ]
      },
      {
        "type": "subcategory",
        "label": "Request Configuration",
        "ids": [
          "Eligibility/PayerId",
          "Eligibility/ProviderNPI",
          "Eligibility/SubmitterId"
        ]
      }
    ],
    "Autism Care": [
        "AutismCare/AutismCareOverview",
      {
        "type": "subcategory",
        "label": "Getting Started",
        "ids": [
        "AutismCare/Sitemap",
        "AutismCare/IntakeRep",
        "AutismCare/Scheduler"
          
        ]
      },
      {
        "type": "subcategory",
        "label": "AdminSetup",
        "ids": [
        "AutismCare/Account",
        "Autismcare/GoalBankLibrary",
        "Autismcare/HealthcareService",
        "Autismcare/InsurancePlan",
        "Autismcare/Location",
        "Autismcare/QualificationDefinition"
      
        ]
      },
      {
        "type": "subcategory",
        "label": "ClinicalSetup",
        "ids": [
        "AutismCare/Authorizations",
        "Autismcare/CareTeamAssignments",
        "Autismcare/Contacts",
        "Autismcare/Coverage"      
        ]
      },
      {
        "type": "subcategory",
        "label": "Patients",
        "ids": [
        "AutismCare/PatientDemographics", 
        "AutismCare/PatientRelatedContacts",
        "AutismCare/PatientMedicalInfo", 
        "AutismCare/PatientCoverage"
          
        ]
      },
      {
        "type": "subcategory",
        "label": "Practitioners",
        "ids": [
        "AutismCare/PractitionerBasicInfo", 
        "AutismCare/PractitionerQualifications",
        "AutismCare/PractitionerRole",
        "AutismCare/PractitionerCareTeamAssignments", 
        "AutismCare/PractitionerEncounters", 
        "AutismCare/PractitionerCalendar"
          
        ]
      },
      {
        "type": "subcategory",
        "label": "Encounters",
        "ids": [
        "AutismCare/RecurringEncounters",
        "AutismCare/SingleEncounters",
        "AutismCare/GeneratingEncounters" 
      
        ]
      },
      {
        "type": "subcategory",
        "label": "Schedule Assistance",
        "ids": [
        "AutismCare/ScheduleAssistance"  
      
        ]
      }
    ],
    "Note Autism Care": [
      "Note/NoteAppMainNavigation"
    ]
  }
}